wailord/__init__.py
wailord/cli.py
wailord/exp/__init__.py
wailord/exp/cookies.py
wailord/exp/plotter.py
wailord/io/__init__.py
wailord/io/inp.py
wailord/io/inputOrca.py
wailord/io/orca.py
wailord/io/sv.py
wailord/io/xyz.py
wailord/utils.py
wailord/wailord.py
wailord_templates/basicExperiment/cookiecutter.json
wailord_templates/basicExperiment/hooks/post_gen_project.py
wailord_templates/basicExperiment/hooks/pre_gen_project.py
wailord_templates/basicExperiment/{{cookiecutter.project_slug}}/basejob.sh
wailord_templates/basicExperiment/{{cookiecutter.project_slug}}/orca.yml
wailord_templates/basicExperiment/{{cookiecutter.project_slug}}/readme.md
wailord-0.0.2.dist-info/entry_points.txt
wailord-0.0.2.dist-info/LICENSE
wailord-0.0.2.dist-info/WHEEL
wailord-0.0.2.dist-info/METADATA
wailord-0.0.2.dist-info/RECORD
