Metadata-Version: 2.1
Name: wailord
Version: 0.0.2
Summary: Wailord is a python library to interact with ORCA
Home-page: https://wailord.xyz
License: GNU General Public License v3
Keywords: wailord,quantum chemistry,orca
Author: Rohit Goswami
Author-email: rog32@hi.is
Requires-Python: >=3.7,<4.0
Classifier: Development Status :: 2 - Pre-Alpha
Classifier: Intended Audience :: Developers
Classifier: License :: OSI Approved :: GNU General Public License v3 (GPLv3)
Classifier: License :: Other/Proprietary License
Classifier: Natural Language :: English
Classifier: Programming Language :: Python :: 3
Classifier: Programming Language :: Python :: 3.5
Classifier: Programming Language :: Python :: 3.6
Classifier: Programming Language :: Python :: 3.7
Classifier: Programming Language :: Python :: 3.8
Classifier: Programming Language :: Python :: 3.9
Provides-Extra: test
Requires-Dist: Jinja2 (>=2.11.2,<3.0.0)
Requires-Dist: Pint (>=0.16.1,<0.17.0)
Requires-Dist: Pint-Pandas (>=0.1,<0.2)
Requires-Dist: Sphinx (>=3.3.1,<4.0.0)
Requires-Dist: ase (>=3.20.1,<4.0.0)
Requires-Dist: black (>=20.8b1,<21.0)
Requires-Dist: click (>=7.0)
Requires-Dist: cookiecutter (>=1.7.2,<2.0.0)
Requires-Dist: flake8 (>=3.8.4,<4.0.0)
Requires-Dist: konfik (>=2.0.0,<3.0.0)
Requires-Dist: pandas (>=1.1.3,<2.0.0)
Requires-Dist: parsimonious (>=0.8.1,<0.9.0)
Requires-Dist: pytest-datadir (>=1.3.1,<2.0.0)
Requires-Dist: releases (>=1.6.3,<2.0.0)
Requires-Dist: scipy (>=1.5.4,<2.0.0)
Requires-Dist: siuba (>=0.0.24,<0.0.25)
Requires-Dist: sphinx-autobuild (>=2020.9.1,<2021.0.0)
Requires-Dist: sphinx-comments (>=0.0.3,<0.0.4)
Requires-Dist: sphinx-copybutton (>=0.3.1,<0.4.0)
Requires-Dist: sphinx-fasvg (>=0.1.3,<0.2.0)
Requires-Dist: sphinx-issues (>=1.2.0,<2.0.0)
Requires-Dist: sphinx-library (>=1.1.2,<2.0.0)
Requires-Dist: sphinx-minipres (>=0.2.1,<0.3.0)
Requires-Dist: sphinx-proof (>=0.0.3,<0.0.4)
Requires-Dist: sphinx-sitemap (>=2.2.0,<3.0.0)
Requires-Dist: sphinx-togglebutton (>=0.2.3,<0.3.0)
Requires-Dist: sphinx-versions (>=1.1.3,<2.0.0)
Requires-Dist: sphinxcontrib-apidoc (>=0.3.0,<0.4.0)
Requires-Dist: sphinxcontrib-doxylink (>=1.6.1,<2.0.0)
Requires-Dist: sphinxcontrib-github_ribbon (>=0.9.0,<0.10.0)
Requires-Dist: sphinxcontrib.contributors (>=1.0,<2.0)
Requires-Dist: vg (>=1.9.0,<2.0.0)
Project-URL: Bug Tracker, https://github.com/HaoZeke/wailord/issues
Project-URL: Documentation, https://wailord.xyz
Project-URL: Repository, https://github.com/HaoZeke/wailord
